academy3AI.py
academy3AI-1.0.6.dist-info/METADATA
academy3AI-1.0.6.dist-info/WHEEL
academy3AI-1.0.6.dist-info/top_level.txt
academy3AI-1.0.6.dist-info/RECORD
