Metadata-Version: 2.1
Name: academy3AI
Version: 1.0.6
Summary: Academy 4 Summer Course
